cyto/__init__.py
cyto/_extra/__init__.py
cyto/_extra/_errors.py
cyto/_version.py
cyto/app/__init__.py
cyto/app/_app.py
cyto/app/_error.py
cyto/app/_inject.py
cyto/app/_settings.py
cyto/basic/__init__.py
cyto/basic/_dict.py
cyto/settings/__init__.py
cyto/settings/_autofill.py
cyto/settings/sources/__init__.py
cyto/settings/sources/cli/__init__.py
cyto/settings/sources/cli/_cli.py
cyto/settings/sources/glob/__init__.py
cyto/settings/sources/glob/_glob.py
cyto-0.3.2.dist-info/LICENSE.txt
cyto-0.3.2.dist-info/WHEEL
cyto-0.3.2.dist-info/METADATA
cyto-0.3.2.dist-info/RECORD
