Metadata-Version: 2.1
Name: cyto
Version: 0.3.2
Summary: SBT Instruments' framework for Python-based applications
Home-page: https://github.com/sbtinstruments/cyto
License: MIT
Author: Frederik Peter Aalund
Author-email: fpa@sbtinstruments.com
Requires-Python: >=3.8,<4.0
Classifier: License :: OSI Approved :: MIT License
Classifier: Programming Language :: Python :: 3
Classifier: Programming Language :: Python :: 3.8
Classifier: Programming Language :: Python :: 3.9
Provides-Extra: all
Provides-Extra: app
Provides-Extra: settings
Provides-Extra: settings.sources.cli
Provides-Extra: settings.sources.toml
Requires-Dist: anyio (>=2.0.2,<3.0.0); extra == "all" or extra == "app"
Requires-Dist: click (>=7.1.2,<8.0.0); extra == "all" or extra == "settings.sources.cli"
Requires-Dist: pydantic (>=1.8.1,<2.0.0); extra == "all" or extra == "app" or extra == "settings"
Requires-Dist: toml (>=0.10.2,<0.11.0); extra == "all" or extra == "settings.sources.toml"
Project-URL: Repository, https://github.com/sbtinstruments/cyto
